Classfile /Users/libo/Documents/GitHub/projects/demo/target/classes/com/gzhennaxia/demo/singleton/Singleton6.class
  Last modified 2020年10月22日; size 1087 bytes
  MD5 checksum 44ed07884405244f19a3963a93b685e8
  Compiled from "Singleton6.java"
public final class com.gzhennaxia.demo.design_pattern.singleton.Singleton6 extends java.lang.Enum<com.gzhennaxia.demo.design_pattern.singleton.Singleton6>
  minor version: 0
  major version: 52
  flags: (0x4031) ACC_PUBLIC, ACC_FINAL, ACC_SUPER, ACC_ENUM
  this_class: #4                          // com/gzhennaxia/demo/singleton/Singleton6
  super_class: #10                        // java/lang/Enum
  interfaces: 0, fields: 2, methods: 4, attributes: 2
Constant pool:
   #1 = Fieldref           #4.#36         // com/gzhennaxia/demo/singleton/Singleton6.$VALUES:[Lcom/gzhennaxia/demo/singleton/Singleton6;
   #2 = Methodref          #37.#38        // "[Lcom/gzhennaxia/demo/singleton/Singleton6;".clone:()Ljava/lang/Object;
   #3 = Class              #14            // "[Lcom/gzhennaxia/demo/singleton/Singleton6;"
   #4 = Class              #39            // com/gzhennaxia/demo/singleton/Singleton6
   #5 = Methodref          #10.#40        // java/lang/Enum.valueOf:(Ljava/lang/Class;Ljava/lang/String;)Ljava/lang/Enum;
   #6 = Methodref          #10.#41        // java/lang/Enum."<init>":(Ljava/lang/String;I)V
   #7 = String             #11            // INSTANCE
   #8 = Methodref          #4.#41         // com/gzhennaxia/demo/singleton/Singleton6."<init>":(Ljava/lang/String;I)V
   #9 = Fieldref           #4.#42         // com/gzhennaxia/demo/singleton/Singleton6.INSTANCE:Lcom/gzhennaxia/demo/singleton/Singleton6;
  #10 = Class              #43            // java/lang/Enum
  #11 = Utf8               INSTANCE
  #12 = Utf8               Lcom/gzhennaxia/demo/singleton/Singleton6;
  #13 = Utf8               $VALUES
  #14 = Utf8               [Lcom/gzhennaxia/demo/singleton/Singleton6;
  #15 = Utf8               values
  #16 = Utf8               ()[Lcom/gzhennaxia/demo/singleton/Singleton6;
  #17 = Utf8               Code
  #18 = Utf8               LineNumberTable
  #19 = Utf8               valueOf
  #20 = Utf8               (Ljava/lang/String;)Lcom/gzhennaxia/demo/singleton/Singleton6;
  #21 = Utf8               LocalVariableTable
  #22 = Utf8               name
  #23 = Utf8               Ljava/lang/String;
  #24 = Utf8               MethodParameters
  #25 = Utf8               <init>
  #26 = Utf8               (Ljava/lang/String;I)V
  #27 = Utf8               this
  #28 = Utf8               $enum$name
  #29 = Utf8               $enum$ordinal
  #30 = Utf8               Signature
  #31 = Utf8               ()V
  #32 = Utf8               <clinit>
  #33 = Utf8               Ljava/lang/Enum<Lcom/gzhennaxia/demo/singleton/Singleton6;>;
  #34 = Utf8               SourceFile
  #35 = Utf8               Singleton6.java
  #36 = NameAndType        #13:#14        // $VALUES:[Lcom/gzhennaxia/demo/singleton/Singleton6;
  #37 = Class              #14            // "[Lcom/gzhennaxia/demo/singleton/Singleton6;"
  #38 = NameAndType        #44:#45        // clone:()Ljava/lang/Object;
  #39 = Utf8               com/gzhennaxia/demo/singleton/Singleton6
  #40 = NameAndType        #19:#46        // valueOf:(Ljava/lang/Class;Ljava/lang/String;)Ljava/lang/Enum;
  #41 = NameAndType        #25:#26        // "<init>":(Ljava/lang/String;I)V
  #42 = NameAndType        #11:#12        // INSTANCE:Lcom/gzhennaxia/demo/singleton/Singleton6;
  #43 = Utf8               java/lang/Enum
  #44 = Utf8               clone
  #45 = Utf8               ()Ljava/lang/Object;
  #46 = Utf8               (Ljava/lang/Class;Ljava/lang/String;)Ljava/lang/Enum;
{
  public static final com.gzhennaxia.demo.design_pattern.singleton.Singleton6 INSTANCE;
    descriptor: Lcom/gzhennaxia/demo/singleton/Singleton6;
    flags: (0x4019) ACC_PUBLIC, ACC_STATIC, ACC_FINAL, ACC_ENUM

  public static com.gzhennaxia.demo.design_pattern.singleton.Singleton6[] values();
    descriptor: ()[Lcom/gzhennaxia/demo/singleton/Singleton6;
    flags: (0x0009) ACC_PUBLIC, ACC_STATIC
    Code:
      stack=1, locals=0, args_size=0
         0: getstatic     #1                  // Field $VALUES:[Lcom/gzhennaxia/demo/singleton/Singleton6;
         3: invokevirtual #2                  // Method "[Lcom/gzhennaxia/demo/singleton/Singleton6;".clone:()Ljava/lang/Object;
         6: checkcast     #3                  // class "[Lcom/gzhennaxia/demo/singleton/Singleton6;"
         9: areturn
      LineNumberTable:
        line 7: 0

  public static com.gzhennaxia.demo.design_pattern.singleton.Singleton6 valueOf(java.lang.String);
    descriptor: (Ljava/lang/String;)Lcom/gzhennaxia/demo/singleton/Singleton6;
    flags: (0x0009) ACC_PUBLIC, ACC_STATIC
    Code:
      stack=2, locals=1, args_size=1
         0: ldc           #4                  // class com/gzhennaxia/demo/singleton/Singleton6
         2: aload_0
         3: invokestatic  #5                  // Method java/lang/Enum.valueOf:(Ljava/lang/Class;Ljava/lang/String;)Ljava/lang/Enum;
         6: checkcast     #4                  // class com/gzhennaxia/demo/singleton/Singleton6
         9: areturn
      LineNumberTable:
        line 7: 0
      LocalVariableTable:
        Start  Length  Slot  Name   Signature
            0      10     0  name   Ljava/lang/String;
    MethodParameters:
      Name                           Flags
      name                           mandated

  static {};
    descriptor: ()V
    flags: (0x0008) ACC_STATIC
    Code:
      stack=4, locals=0, args_size=0
         0: new           #4                  // class com/gzhennaxia/demo/singleton/Singleton6
         3: dup
         4: ldc           #7                  // String INSTANCE
         6: iconst_0
         7: invokespecial #8                  // Method "<init>":(Ljava/lang/String;I)V
        10: putstatic     #9                  // Field INSTANCE:Lcom/gzhennaxia/demo/singleton/Singleton6;
        13: iconst_1
        14: anewarray     #4                  // class com/gzhennaxia/demo/singleton/Singleton6
        17: dup
        18: iconst_0
        19: getstatic     #9                  // Field INSTANCE:Lcom/gzhennaxia/demo/singleton/Singleton6;
        22: aastore
        23: putstatic     #1                  // Field $VALUES:[Lcom/gzhennaxia/demo/singleton/Singleton6;
        26: return
      LineNumberTable:
        line 8: 0
        line 7: 13
}
Signature: #33                          // Ljava/lang/Enum<Lcom/gzhennaxia/demo/singleton/Singleton6;>;
SourceFile: "Singleton6.java"
iMacDev110:projects libo$
